obnb/__init__.py
obnb/exception.py
obnb/typing.py
obnb/config/__init__.py
obnb/config/logger_config.py
obnb/data/__init__.py
obnb/data/base.py
obnb/data/annotated_ontology/__init__.py
obnb/data/annotated_ontology/base.py
obnb/data/annotated_ontology/diseases.py
obnb/data/annotated_ontology/disgenet.py
obnb/data/annotated_ontology/go.py
obnb/data/annotated_ontology/hpo.py
obnb/data/annotation/__init__.py
obnb/data/annotation/base.py
obnb/data/annotation/diseases.py
obnb/data/annotation/disgenet.py
obnb/data/annotation/gene_ontology.py
obnb/data/annotation/human_phenotype_ontology.py
obnb/data/experimental/__init__.py
obnb/data/experimental/alevinfry.py
obnb/data/network/__init__.py
obnb/data/network/base.py
obnb/data/network/biogrid.py
obnb/data/network/bioplex.py
obnb/data/network/comppi.py
obnb/data/network/consensuspathdb.py
obnb/data/network/funcoup.py
obnb/data/network/hippie.py
obnb/data/network/humanbase.py
obnb/data/network/humannet.py
obnb/data/network/humap.py
obnb/data/network/huri.py
obnb/data/network/omnipath.py
obnb/data/network/pcnet.py
obnb/data/network/proteomehd.py
obnb/data/network/signor.py
obnb/data/network/string.py
obnb/data/ontology/__init__.py
obnb/data/ontology/base.py
obnb/data/ontology/gene_ontology.py
obnb/data/ontology/mondo.py
obnb/dataset/__init__.py
obnb/dataset/base.py
obnb/dataset/dataset.py
obnb/dataset/dataset_dgl.py
obnb/dataset/dataset_pyg.py
obnb/ext/__init__.py
obnb/ext/grape.py
obnb/ext/orbital_features.py
obnb/ext/pecanpy.py
obnb/ext/sknetwork.py
obnb/feature/__init__.py
obnb/feature/base.py
obnb/feature/multifeat.py
obnb/feature/singlefeat.py
obnb/graph/__init__.py
obnb/graph/base.py
obnb/graph/dense.py
obnb/graph/ontology.py
obnb/graph/sparse.py
obnb/label/__init__.py
obnb/label/collection.py
obnb/label/filters/__init__.py
obnb/label/filters/base.py
obnb/label/filters/existence_filter.py
obnb/label/filters/negative_generator.py
obnb/label/filters/nonred.py
obnb/label/filters/pairwise_filter.py
obnb-0.1.0.dist-info/LICENSE
obnb-0.1.0.dist-info/METADATA
obnb-0.1.0.dist-info/WHEEL
obnb-0.1.0.dist-info/top_level.txt
obnb-0.1.0.dist-info/RECORD
