Metadata-Version: 2.1
Name: obnb
Version: 0.1.0
Summary: A Python toolkit for biological network learning evaluation
Author-email: Remy Liu <liurenmi@msu.edu>
License: MIT
Project-URL: home, https://github.com/krishnanlab/obnb
Project-URL: bug-tracker, https://github.com/krishnanlab/obnb/issues
Keywords: Data Processing,Gene Classification,Machine Learning,Network Biology,Network Repositories
Classifier: Development Status :: 4 - Beta
Classifier: License :: OSI Approved :: MIT License
Classifier: Programming Language :: Python :: 3 :: Only
Classifier: Programming Language :: Python :: 3.8
Classifier: Programming Language :: Python :: 3.9
Classifier: Programming Language :: Python
Classifier: Topic :: Scientific/Engineering :: Artificial Intelligence
Classifier: Topic :: Scientific/Engineering :: Bio-Informatics
Requires-Python: >=3.8
License-File: LICENSE
Requires-Dist: matplotlib
Requires-Dist: mygene
Requires-Dist: ndex2
Requires-Dist: numpy (>=1.20.0)
Requires-Dist: pyOpenSSL (>=23.1.1)
Requires-Dist: pyyaml
Requires-Dist: requests
Requires-Dist: scikit-learn (>=1.0.0)
Requires-Dist: scipy
Requires-Dist: tqdm
Requires-Dist: outdated
Provides-Extra: dev
Requires-Dist: bump2version ; extra == 'dev'
Requires-Dist: click ; extra == 'dev'
Requires-Dist: jinja2 ; extra == 'dev'
Requires-Dist: parameterized ; extra == 'dev'
Requires-Dist: pre-commit ; extra == 'dev'
Requires-Dist: pytest ; extra == 'dev'
Requires-Dist: pytest-cov ; extra == 'dev'
Requires-Dist: pytest-mock ; extra == 'dev'
Requires-Dist: pytest-subtests ; extra == 'dev'
Requires-Dist: pytest-xdist ; extra == 'dev'
Requires-Dist: requests-mock ; extra == 'dev'
Requires-Dist: tabulate ; extra == 'dev'
Requires-Dist: tox ; extra == 'dev'
Provides-Extra: doc
Requires-Dist: sphinx ; extra == 'doc'
Requires-Dist: sphinx-autodoc-typehints ; extra == 'doc'
Requires-Dist: sphinx-rtd-theme ; extra == 'doc'
Requires-Dist: sphinxcontrib-napoleon ; extra == 'doc'
Requires-Dist: yacs ; extra == 'doc'
Provides-Extra: ext
Requires-Dist: grape ; extra == 'ext'
Requires-Dist: pecanpy ; extra == 'ext'
Requires-Dist: scikit-network ; extra == 'ext'
Requires-Dist: networkx ; extra == 'ext'
Provides-Extra: full
Requires-Dist: obnb[ext,pyroe] ; extra == 'full'
Provides-Extra: pyroe
Requires-Dist: pyroe ; extra == 'pyroe'
Requires-Dist: scanpy ; extra == 'pyroe'
